feedendum/__init__.py
feedendum/__version__.py
feedendum/atom.py
feedendum/exceptions.py
feedendum/feed.py
feedendum/rdf.py
feedendum/rss.py
feedendum/utils.py
feedendum-0.4.0.dist-info/METADATA
feedendum-0.4.0.dist-info/WHEEL
feedendum-0.4.0.dist-info/licenses/LICENSE
feedendum-0.4.0.dist-info/RECORD
