Metadata-Version: 2.3
Name: feedendum
Version: 0.4.0
Summary: A Utilities to read and write RSS and Atom feeds.
Project-URL: Homepage, https://github.com/timendum/feedendum
Author-email: Timendum <timendum@gmail.com>
License:                     GNU AFFERO GENERAL PUBLIC LICENSE
License-File: LICENSE
Classifier: License :: OSI Approved :: GNU Affero General Public License v3
Classifier: Programming Language :: Python
Classifier: Programming Language :: Python :: 3
Classifier: Programming Language :: Python :: 3.10
Classifier: Topic :: Software Development :: Libraries
Classifier: Topic :: Text Processing :: Markup :: XML
Requires-Python: >=3.10
Requires-Dist: lxml
Provides-Extra: http
Requires-Dist: requests; extra == 'http'
